odoo/addons/ai_oca_bridge_mrp/README.rst
odoo/addons/ai_oca_bridge_mrp/__init__.py
odoo/addons/ai_oca_bridge_mrp/__manifest__.py
odoo/addons/ai_oca_bridge_mrp/demo/ai_bridge_demo.xml
odoo/addons/ai_oca_bridge_mrp/i18n/ai_oca_bridge_mrp.pot
odoo/addons/ai_oca_bridge_mrp/i18n/it.po
odoo/addons/ai_oca_bridge_mrp/models/__init__.py
odoo/addons/ai_oca_bridge_mrp/models/mrp_workorder.py
odoo/addons/ai_oca_bridge_mrp/readme/CONFIGURE.md
odoo/addons/ai_oca_bridge_mrp/readme/CONTRIBUTORS.md
odoo/addons/ai_oca_bridge_mrp/readme/DESCRIPTION.md
odoo/addons/ai_oca_bridge_mrp/readme/USAGE.md
odoo/addons/ai_oca_bridge_mrp/static/description/icon.png
odoo/addons/ai_oca_bridge_mrp/static/description/index.html
odoo/addons/ai_oca_bridge_mrp/tests/__init__.py
odoo/addons/ai_oca_bridge_mrp/tests/test_mrp_ai_bridge.py
odoo_addon_ai_oca_bridge_mrp-16.0.2.0.0.dist-info/METADATA
odoo_addon_ai_oca_bridge_mrp-16.0.2.0.0.dist-info/WHEEL
odoo_addon_ai_oca_bridge_mrp-16.0.2.0.0.dist-info/top_level.txt
odoo_addon_ai_oca_bridge_mrp-16.0.2.0.0.dist-info/RECORD
